{
  "id": "tech_mechanized_mining",
  "name": {
    "en": "Mechanized Mining",
    "zh": "机械化开采"
  },
  "category": "technology",
  "subcategory": "engineering",
  "dlc": null,
  "lore": "应用机械工程学进行采矿是任何工业社会的基本需求。",
  "traits": [],
  "tags": [
    "technology",
    "engineering"
  ],
  "technology": {
    "area": "engineering",
    "tier": "0",
    "cost": "0",
    "category": null,
    "prerequisites": [],
    "features": [],
    "weight": null,
    "is_repeatable": false
  },
  "relations": [
    {
      "type": "提及",
      "target": "trait_machine_unit"
    },
    {
      "type": "关联",
      "target": "null_void_beam"
    },
    {
      "type": "关联",
      "target": "tech_adaptive_bureaucracy"
    },
    {
      "type": "关联",
      "target": "tech_adaptive_combat_algorithms"
    },
    {
      "type": "关联",
      "target": "tech_administrative_ai"
    }
  ]
}