{
  "id": "tech_unusual_senses",
  "name": {
    "en": "Unusual Senses",
    "zh": "异常传感"
  },
  "category": "technology",
  "subcategory": "physics",
  "dlc": "First Contact",
  "lore": "没有什么比自然进化更有创新力的了。通过研究前超光速文明社会是如何看待它们的世界，我们设计了新的方法以探测不速之舰船。",
  "traits": [],
  "tags": [
    "technology",
    "physics"
  ],
  "technology": {
    "area": "physics",
    "tier": "2",
    "cost": "@tier2cost3",
    "category": null,
    "prerequisites": [],
    "features": [],
    "weight": "0",
    "is_repeatable": false
  },
  "relations": [
    {
      "type": "关联",
      "target": "null_void_beam"
    },
    {
      "type": "关联",
      "target": "tech_adaptive_bureaucracy"
    },
    {
      "type": "关联",
      "target": "tech_adaptive_combat_algorithms"
    },
    {
      "type": "关联",
      "target": "tech_administrative_ai"
    },
    {
      "type": "关联",
      "target": "tech_advanced_metallurgy_1"
    }
  ]
}